vizrecurse/__init__.py
vizrecurse/display.py
vizrecurse/py.typed
vizrecurse/vizzy.py
vizrecurse-1.1.3.dist-info/METADATA
vizrecurse-1.1.3.dist-info/WHEEL
vizrecurse-1.1.3.dist-info/top_level.txt
vizrecurse-1.1.3.dist-info/RECORD
