Metadata-Version: 2.1
Name: vizrecurse
Version: 1.1.3
Summary: Bare bones library to vizualize recursion with one line of code.
Author: Cody Pedersen
Classifier: Programming Language :: Python :: 3.10
Classifier: Operating System :: OS Independent
Classifier: Intended Audience :: Developers
Classifier: Intended Audience :: Education
Requires-Python: >=3.10
Requires-Dist: astroid ==3.2.2
Requires-Dist: contourpy ==1.2.1
Requires-Dist: cycler ==0.12.1
Requires-Dist: dill ==0.3.8
Requires-Dist: fonttools ==4.51.0
Requires-Dist: graphviz ==0.20.3
Requires-Dist: isort ==5.13.2
Requires-Dist: kiwisolver ==1.4.5
Requires-Dist: matplotlib ==3.9.0
Requires-Dist: mccabe ==0.7.0
Requires-Dist: networkx ==3.3
Requires-Dist: numpy ==1.26.4
Requires-Dist: packaging ==24.0
Requires-Dist: pillow ==10.3.0
Requires-Dist: platformdirs ==4.2.2
Requires-Dist: pydot ==2.0.0
Requires-Dist: pygraphviz ==1.13
Requires-Dist: pylint ==3.2.2
Requires-Dist: pyparsing ==3.1.2
Requires-Dist: python-dateutil ==2.9.0.post0
Requires-Dist: six ==1.16.0
Requires-Dist: tomli ==2.0.1
Requires-Dist: tomlkit ==0.12.5
Requires-Dist: typing-extensions ==4.12.0
